DarkWebSearch/__init__.py
DarkWebSearch/core.py
darkwebsearch-1.0.1.dist-info/licenses/LICENSE
darkwebsearch-1.0.1.dist-info/METADATA
darkwebsearch-1.0.1.dist-info/WHEEL
darkwebsearch-1.0.1.dist-info/top_level.txt
darkwebsearch-1.0.1.dist-info/RECORD
